fastclf/__init__.py
fastclf/__version__.py
fastclf/decomposition.py
fastclf/modelinfo.py
fastclf-0.1.0.dist-info/LICENSE
fastclf-0.1.0.dist-info/METADATA
fastclf-0.1.0.dist-info/WHEEL
fastclf-0.1.0.dist-info/top_level.txt
fastclf-0.1.0.dist-info/RECORD
