Metadata-Version: 2.1
Name: fastclf
Version: 0.1.0
Summary: fastclf is a package that makes it easy to test different models on different datasets. 
Home-page: https://github.com/rhcproc/fastclf
Author: Hans Park
Author-email: rhcproc@gmail.com
License: MIT
Classifier: Programming Language :: Python :: 3.6
Classifier: Programming Language :: Python :: 3.7
Classifier: Programming Language :: Python :: 3.8
Classifier: Programming Language :: Python :: 3.9
Classifier: Programming Language :: Python :: 3.10
Classifier: License :: OSI Approved :: MIT License
Classifier: Operating System :: OS Independent
Requires-Python: >=3.5
License-File: LICENSE
Requires-Dist: pandas
Requires-Dist: scikit-learn
